AUTHORS.rst
CONTRIBUTING.rst
HISTORY.rst
LICENSE
MANIFEST.in
README.rst
setup.cfg
setup.py
docs/Makefile
docs/authors.rst
docs/conf.py
docs/contributing.rst
docs/history.rst
docs/index.rst
docs/installation.rst
docs/make.bat
docs/readme.rst
docs/usage.rst
langchangetrack/__init__.py
langchangetrack/langchangetrack.py
langchangetrack.egg-info/PKG-INFO
langchangetrack.egg-info/SOURCES.txt
langchangetrack.egg-info/dependency_links.txt
langchangetrack.egg-info/not-zip-safe
langchangetrack.egg-info/requires.txt
langchangetrack.egg-info/top_level.txt
langchangetrack/corpusreaders/__init__.py
langchangetrack/corpusreaders/plainngramscorpus.py
langchangetrack/cpdetection/detect_changepoints_word_ts.py
langchangetrack/scripts/detect_cp_distributional.sh
langchangetrack/scripts/detect_cp_freq.sh
langchangetrack/scripts/detect_cp_pos.sh
langchangetrack/tsconstruction/__init__.py
langchangetrack/tsconstruction/displacements.py
langchangetrack/tsconstruction/dump_timeseries.py
langchangetrack/tsconstruction/distributional/__init__.py
langchangetrack/tsconstruction/distributional/corpustoembeddings.py
langchangetrack/tsconstruction/distributional/scripts/embedding_displacements.py
langchangetrack/tsconstruction/distributional/scripts/learn_map.py
langchangetrack/tsconstruction/distributional/scripts/train_embeddings_ngrams.py
langchangetrack/tsconstruction/freq/scripts/create_freq_timeseries.py
langchangetrack/tsconstruction/syntactic/scripts/pos_displacements.py
langchangetrack/utils/LocalLinearRegression.py
langchangetrack/utils/__init__.py
langchangetrack/utils/dummy_regressor.py
langchangetrack/utils/entropy.py
langchangetrack/utils/scripts/common_vocab.py
langchangetrack/utils/scripts/freq_count.py
tests/__init__.py
tests/test_langchangetrack.py