Metadata-Version: 1.1
Name: langchangetrack
Version: 0.1.0
Summary: Package for statistically significant language change.
Home-page: https://github.com/viveksck/langchangetrack
Author: Vivek Kulkarni
Author-email: viveksck@gmail.com
License: BSD
Keywords: langchangetrack
Platform: UNKNOWN
Classifier: Development Status :: 2 - Pre-Alpha
Classifier: Intended Audience :: Developers
Classifier: License :: OSI Approved :: BSD License
Classifier: Natural Language :: English
Classifier: Programming Language :: Python :: 2
Classifier: Programming Language :: Python :: 2.6
Classifier: Programming Language :: Python :: 2.7
Classifier: Programming Language :: Python :: 3
Classifier: Programming Language :: Python :: 3.3
Classifier: Programming Language :: Python :: 3.4
